yatl/__init__.py
yatl/compiler.py
yatl/parser.py
yatl/runtime.py
yatl/utils.py
yatl/validator.py
usepolvo_yatl-0.2.2.dist-info/METADATA
usepolvo_yatl-0.2.2.dist-info/WHEEL
usepolvo_yatl-0.2.2.dist-info/top_level.txt
usepolvo_yatl-0.2.2.dist-info/RECORD
