Metadata-Version: 2.1
Name: usepolvo-yatl
Version: 0.2.2
Summary: A Python implementation of YATL (Yet Another Tentacle Language)
Author-email: Caio Pizzol <caio@usepolvo.com>
License: MIT
Requires-Python: >=3.7
Requires-Dist: PyYAML==6.0.2
